BRIntel/__init__.py
BRIntel/otx/__init__.py
BRIntel/xfe/__init__.py
BRIntel-0.1.dist-info/METADATA
BRIntel-0.1.dist-info/WHEEL
BRIntel-0.1.dist-info/top_level.txt
BRIntel-0.1.dist-info/RECORD
