Metadata-Version: 2.1
Name: BRIntel
Version: 0.1
Summary: Cyber Threat Intelligence (CTI) usando fontes e indicadores de ameaças nacionais, ou até globais, mas com evidencias ou indicadores nacionais do Brasil
Home-page: https://github.com/VaultSEC/BRIntelcollector
Author: VaultSec, Julio Lira, Matheus Oliveira
Author-email: contato@vaultsec.com.br, jul10l1r4@disroot.org, matheusoliveiratux4me@gmail.com
License: GPLv3
Project-URL: Vault Cyber Security, https://vaultsec.com.br/
Project-URL: Github profile, https://github.com/VaultSEC
Keywords: threat intelligence security ibm xforce x-force blueteam search query api exchange otx cti oct OTX otx open threat CTI brazil brasil br
Classifier: Programming Language :: Python :: 3
Classifier: License :: OSI Approved :: GNU General Public License v3 or later (GPLv3+)
Classifier: Operating System :: OS Independent
Classifier: Topic :: Internet
Classifier: Topic :: Security
